pwn_gadget/__init__.py
pwn_gadget/checking.py
pwn_gadget/data_types.py
pwn_gadget/logging.py
pwn_gadget/main.py
pwn_gadget/parser.py
pwn_gadget/util.py
pwn_gadget-0.0.2.dist-info/METADATA
pwn_gadget-0.0.2.dist-info/WHEEL
pwn_gadget-0.0.2.dist-info/top_level.txt
pwn_gadget-0.0.2.dist-info/RECORD
