Metadata-Version: 2.1
Name: pwn-gadget
Version: 0.0.2
Summary: Find satisfiable one gadgets from a running gdb instance
Home-page: https://github.com/zolutal/pwn_gadget
Classifier: Programming Language :: Python :: 3
Classifier: Programming Language :: Python :: 3.8
Requires-Python: >=3.8
